checkey-sklearn/__init__.py
checkey-sklearn/improving_naive_bayes.py
checkey-sklearn/topsis.py
chlearn/__init__.py
chlearn/improving_naive_bayes.py
chlearn/topsis.py
chlearn-0.1.0.dist-info/LICENSE.txt
chlearn-0.1.0.dist-info/METADATA
chlearn-0.1.0.dist-info/WHEEL
chlearn-0.1.0.dist-info/top_level.txt
chlearn-0.1.0.dist-info/RECORD
