Metadata-Version: 2.1
Name: chlearn
Version: 0.1.0
Summary: 自己平时会使用的一些统计学和数学模型,目前有两个改进的朴素贝叶斯算法和一个TOPSIS
Author: Checkey01
Author-email: Chiaki2048@outlook.com
Keywords: Machine Learning,Python
License-File: LICENSE.txt
Requires-Dist: numpy
Requires-Dist: pandas
Requires-Dist: scikit-learn
